[
  {
		"id": 0,
		"slug": "book-store",
		"name": "Book Store",
		"excerpt": "Онлайн-магазин для продажу/покупки різноманітних книг у різних форматах.",
		"siteUrl": "https://google.com",
		"time": "2 месяця",
		"price": "800$",
		"preview": "book-store/book-store.webp",
		"tags": [1, 3]
	},
	{
		"id": 1,
		"slug": "movies",
		"name": "TOP 250 Movies",
		"excerpt": "Сайт с топ 250, популярними фільмами по версії imdb.",
		"siteUrl": "https://validol4ik.github.io/250movies",
		"time": "12 днів",
		"price": "480$",
		"preview": "movies/movies.webp",
		"tags": [3]
	},
	{
		"id": 2,
		"slug": "business-scheme",
		"name": "Business Scheme",
		"excerpt": "Сайт компанії Business Scheme для продажу рекламних послуг",
		"siteUrl": "http://busisckhem.biz",
		"time": "2 месяця",
		"price": "900$",
		"preview": "business/business.webp",
		"tags": [3]
	},
  {
		"id": 3,
		"slug": "lucid-theme",
		"name": "Lucid Theme",
		"excerpt": "Верстка продажного лендінга WordPress теми Lucid",
		"siteUrl": "https://validol4ik.github.io/lucid",
		"time": "4 дні",
		"price": "160$",
		"preview": "lucid/lucid.webp",
		"tags": [0, 2]
	},
	{
		"id": 4,
		"slug": "spend",
		"name": "Spend",
		"excerpt": "Мобільний додаток для відстежування доходів/витрат.",
		"time": "3 тижні",
		"price": "600$",
		"preview": "spend/spend.webp",
		"tags": [0, 2]
	}
]
